vchasno_crm/__init__.py
vchasno_crm-0.0.1.dist-info/METADATA
vchasno_crm-0.0.1.dist-info/WHEEL
vchasno_crm-0.0.1.dist-info/top_level.txt
vchasno_crm-0.0.1.dist-info/RECORD
