Metadata-Version: 2.1
Name: vchasno_crm
Version: 0.0.1
Summary: vchasno_crm package lock
